lkg/__init__.py
lkg/main.py
lkg-0.2.dist-info/METADATA
lkg-0.2.dist-info/WHEEL
lkg-0.2.dist-info/top_level.txt
lkg-0.2.dist-info/RECORD
