Metadata-Version: 2.1
Name: lkg
Version: 0.2
